pointless_db/__init__.py
pointless_db-0.0.2.dist-info/LICENSE
pointless_db-0.0.2.dist-info/METADATA
pointless_db-0.0.2.dist-info/WHEEL
pointless_db-0.0.2.dist-info/top_level.txt
pointless_db-0.0.2.dist-info/RECORD
