Metadata-Version: 2.1
Name: pointless-db
Version: 0.0.2
Summary: Pointless in-memory database for sqlDash
Home-page: https://github.com/sqlDash/pointless-db-plugin
Author: WardPearce
Author-email: wardpearce@pm.me
License: GPL-3.0
Platform: UNKNOWN
Requires-Python: >=3.6
License-File: LICENSE
